LICENSE.txt
MANIFEST.in
README.rst
setup.py
img/user_guide-_open_browser_with_the_sagemathcell_0001_728px.png
sagecell/__init__.py
sagecell/sagecell.py
sagecell.egg-info/PKG-INFO
sagecell.egg-info/SOURCES.txt
sagecell.egg-info/dependency_links.txt
sagecell.egg-info/entry_points.txt
sagecell.egg-info/requires.txt
sagecell.egg-info/top_level.txt
sagecell.egg-info/zip-safe
sagecell/config/argparse.txt
sagecell/config/messages.txt
sagecell/config/sagecell.ini
scripts/sagecellscript