Metadata-Version: 1.1
Name: sagecell
Version: 0.3rc6
Summary: The SageMathCell installer
Home-page: https://github.com/korniichuk/sagecell
Author: Ruslan Korniichuk
Author-email: ruslan.korniichuk@gmail.com
License: Public Domain
Download-URL: https://github.com/korniichuk/sagecell/archive/0.3.zip
Keywords: installer,python2,sagecell,sagemathcell
Platform: Linux
Classifier: Development Status :: 5 - Production/Stable
Classifier: Environment :: Console
Classifier: Intended Audience :: Developers
Classifier: Intended Audience :: Information Technology
Classifier: Intended Audience :: Science/Research
Classifier: Intended Audience :: System Administrators
Classifier: License :: Public Domain
Classifier: Operating System :: POSIX :: Linux
Classifier: Programming Language :: Python
Classifier: Programming Language :: Python :: 2
Classifier: Programming Language :: Python :: 2.7
Classifier: Programming Language :: Python :: 2 :: Only
Classifier: Topic :: Scientific/Engineering
Classifier: Topic :: System :: Systems Administration
Classifier: Topic :: Utilities
